raylab/__init__.py
raylab/agents/__init__.py
raylab/agents/acktr/__init__.py
raylab/agents/acktr/policy.py
raylab/agents/acktr/trainer.py
raylab/agents/mage/__init__.py
raylab/agents/mage/policy.py
raylab/agents/mage/trainer.py
raylab/agents/mbpo/__init__.py
raylab/agents/mbpo/policy.py
raylab/agents/mbpo/trainer.py
raylab/agents/model_based.py
raylab/agents/naf/__init__.py
raylab/agents/naf/policy.py
raylab/agents/naf/trainer.py
raylab/agents/off_policy.py
raylab/agents/registry.py
raylab/agents/sac/__init__.py
raylab/agents/sac/policy.py
raylab/agents/sac/trainer.py
raylab/agents/sop/__init__.py
raylab/agents/sop/policy.py
raylab/agents/sop/trainer.py
raylab/agents/svg/__init__.py
raylab/agents/svg/inf/__init__.py
raylab/agents/svg/inf/policy.py
raylab/agents/svg/inf/trainer.py
raylab/agents/svg/one/__init__.py
raylab/agents/svg/one/policy.py
raylab/agents/svg/one/trainer.py
raylab/agents/svg/policy.py
raylab/agents/svg/soft/__init__.py
raylab/agents/svg/soft/policy.py
raylab/agents/svg/soft/trainer.py
raylab/agents/td3/__init__.py
raylab/agents/td3/policy.py
raylab/agents/td3/trainer.py
raylab/agents/trainer.py
raylab/agents/trpo/__init__.py
raylab/agents/trpo/policy.py
raylab/agents/trpo/trainer.py
raylab/cli/__init__.py
raylab/cli/best_checkpoint.py
raylab/cli/episode_dashboard.py
raylab/cli/evaluate_checkpoint.py
raylab/cli/experiment.py
raylab/cli/experiment_dashboard.py
raylab/cli/info.py
raylab/cli/module_dashboard.py
raylab/cli/utils.py
raylab/cli/viz.py
raylab/envs/__init__.py
raylab/envs/environments/__init__.py
raylab/envs/environments/cartpole_stateless.py
raylab/envs/environments/hvac.py
raylab/envs/environments/navigation.py
raylab/envs/environments/reservoir.py
raylab/envs/registry.py
raylab/envs/rewards.py
raylab/envs/termination.py
raylab/envs/utils.py
raylab/envs/wrappers/__init__.py
raylab/envs/wrappers/correlated_irrelevant.py
raylab/envs/wrappers/gaussian_random_walks.py
raylab/envs/wrappers/linear_redundant.py
raylab/envs/wrappers/mixins.py
raylab-0.16.0.dist-info/entry_points.txt
raylab-0.16.0.dist-info/LICENSE
raylab-0.16.0.dist-info/WHEEL
raylab-0.16.0.dist-info/METADATA
raylab-0.16.0.dist-info/RECORD
