Metadata-Version: 2.1
Name: raylab
Version: 0.16.0
Summary: Reinforcement learning algorithms in RLlib and PyTorch.
Home-page: https://github.com/angelolovatto/raylab
License: MIT
Keywords: reinforcement-learning,rllib,deep-learning,model-based-rl,pytorch
Author: Ângelo Gregório Lovatto
Author-email: angelolovatto@gmail.com
Requires-Python: >=3.7,<4.0
Classifier: Development Status :: 2 - Pre-Alpha
Classifier: Intended Audience :: Developers
Classifier: License :: OSI Approved :: MIT License
Classifier: Natural Language :: English
Classifier: Programming Language :: Python :: 3
Classifier: Programming Language :: Python :: 3.7
Classifier: Programming Language :: Python :: 3.8
Classifier: Programming Language :: Python :: 3.9
Requires-Dist: bokeh (<2.3.4)
Requires-Dist: cachetools (>=4.1.0,<5.0.0); python_version >= "3.7" and python_version < "4.0"
Requires-Dist: click (>=7.1.2,<8.0.0)
Requires-Dist: dataclasses-json (>=0.5.1,<0.6.0)
Requires-Dist: dm-tree (>=0.1.5,<0.2.0)
Requires-Dist: nnrl (>=0.1.0,<0.2.0)
Requires-Dist: opencv-contrib-python (>=4.4.0,<5.0.0)
Requires-Dist: opencv-python (>=4.2.0,<5.0.0)
Requires-Dist: poetry-version (>=0.1.5,<0.2.0)
Requires-Dist: pytorch-lightning (>=1.3.8,<1.5.0)
Requires-Dist: ray[rllib,tune] (<1.6)
Requires-Dist: sklearn (>=0.0,<0.1)
Requires-Dist: streamlit (>=0.62,<0.86)
Requires-Dist: tabulate (>=0.8.7,<0.9.0)
Requires-Dist: torch (>=1.5.1,<2.0.0)
Project-URL: Repository, https://github.com/angelolovatto/raylab
